vedro_cloud/__init__.py
vedro_cloud/_duration_orderer.py
vedro_cloud/_validate_config.py
vedro_cloud/_vedro_cloud_client.py
vedro_cloud/_vedro_cloud_plugin.py
vedro_cloud/py.typed
vedro_cloud-0.3.2.dist-info/LICENSE
vedro_cloud-0.3.2.dist-info/METADATA
vedro_cloud-0.3.2.dist-info/WHEEL
vedro_cloud-0.3.2.dist-info/top_level.txt
vedro_cloud-0.3.2.dist-info/RECORD
