Metadata-Version: 2.1
Name: vedro-cloud
Version: 0.3.2
Summary: Vedro Cloud plugin
Home-page: https://github.com/vedro-universe/vedro-cloud
Author: Nikita Tsvetkov
Author-email: tsv1@fastmail.com
License: Apache-2.0
Classifier: License :: OSI Approved :: Apache Software License
Classifier: Programming Language :: Python :: 3.8
Classifier: Programming Language :: Python :: 3.9
Classifier: Programming Language :: Python :: 3.10
Classifier: Typing :: Typed
Requires-Python: >=3.8
License-File: LICENSE
Requires-Dist: vedro <2.0,>=1.8.3
Requires-Dist: httpx <1.0,>=0.23
Requires-Dist: rtry <2.0,>=1.4
